infinstor_mlflow_plugin/__init__.py
infinstor_mlflow_plugin/cognito_auth_rest_store.py
infinstor_mlflow_plugin/gc.py
infinstor_mlflow_plugin/infinstor_artifact.py
infinstor_mlflow_plugin/infinstor_backend.py
infinstor_mlflow_plugin/infinstor_deployment_plugin.py
infinstor_mlflow_plugin/login.py
infinstor_mlflow_plugin/run_context_provider.py
infinstor_mlflow_plugin/servicedefs.py
infinstor_mlflow_plugin/sql_store_alchemy.py
infinstor_mlflow_plugin/tokenfile.py
infinstor_mlflow_plugin/transformers.py
infinstor_mlflow_plugin/utils.py
infinstor_mlflow_plugin-2.0.63.data/scripts/mlflow_run_infinstor_backend.sh
infinstor_mlflow_plugin-2.0.63.dist-info/METADATA
infinstor_mlflow_plugin-2.0.63.dist-info/WHEEL
infinstor_mlflow_plugin-2.0.63.dist-info/entry_points.txt
infinstor_mlflow_plugin-2.0.63.dist-info/top_level.txt
infinstor_mlflow_plugin-2.0.63.dist-info/RECORD
