Metadata-Version: 2.1
Name: infinstor-mlflow-plugin
Version: 2.0.63
Summary: InfinStor plugin for MLflow
Requires-Dist: mlflow <3,>=1.21.0
Requires-Dist: jsons
Requires-Dist: kubernetes
Requires-Dist: PyJWT
Requires-Dist: traceback-with-variables
